codeoffer/__init__.py
codeoffer/api.py
codeoffer/app.py
codeoffer/exceptions.py
codeoffer/oauth.py
codeoffer/user.py
codeoffer/utilities.py
codeoffer-1.0.4.dist-info/METADATA
codeoffer-1.0.4.dist-info/WHEEL
codeoffer-1.0.4.dist-info/licenses/LICENSE
codeoffer-1.0.4.dist-info/RECORD
