Metadata-Version: 2.1
Name: codeoffer
Version: 1.0.4
Summary: Python API Wrapper for the public CodeOffer API
Project-URL: Homepage, https://github.com/codeoffer/v1-python-library
Project-URL: Bug Tracker, https://github.com/codeoffer/v1-python-library/issues
Author-email: CodeOffer <contact@codeoffer.net>
License-File: LICENSE
Classifier: Operating System :: OS Independent
Classifier: Programming Language :: Python :: 3
Requires-Python: >=3.7
